VegasAfterglow/__init__.py
VegasAfterglow/_version.py
VegasAfterglow/runner.py
VegasAfterglow/types.py
VegasAfterglow/VegasAfterglowC.cp310-win_amd64.pyd
vegasafterglow-1.1.0.dist-info/METADATA
vegasafterglow-1.1.0.dist-info/WHEEL
vegasafterglow-1.1.0.dist-info/licenses/LICENSE
vegasafterglow-1.1.0.dist-info/RECORD
