Metadata-Version: 2.2
Name: VegasAfterglow
Version: 1.1.0
Summary: MCMC tools for astrophysics
Author-Email: Yihan Wang <yihan.astro@gmail.com>
License: BSD-3-Clause
Requires-Python: >=3.7
Requires-Dist: numpy>=1.20
Requires-Dist: scipy>=1.6
Requires-Dist: pandas>=1.2
Requires-Dist: bilby>=2.1
Requires-Dist: corner>=2.2.1
Requires-Dist: tqdm>=4.0
